mc_lab/MCMC-notes2.pdf
mc_lab/PSIS.py
mc_lab/__init__.py
mc_lab/_rng.py
mc_lab/advanced_rejection_sampling.py
mc_lab/box_muller.py
mc_lab/distribution_comparison.py
mc_lab/fast_inverse_transform.py
mc_lab/gibbs_sampler_2d.py
mc_lab/importance_sampling.py
mc_lab/inverse_transform.py
mc_lab/metropolis_hastings.py
mc_lab/moment_comparison.py
mc_lab/multivariate_gaussian.py
mc_lab/plotting.py
mc_lab/rejection_sampling.py
mc_lab/transformation_methods.py
mc_lab_edu-0.2.7.dist-info/METADATA
mc_lab_edu-0.2.7.dist-info/WHEEL
mc_lab_edu-0.2.7.dist-info/licenses/LICENSE
mc_lab_edu-0.2.7.dist-info/RECORD
