Metadata-Version: 2.4
Name: mc-lab-edu
Version: 0.2.7
Summary: Educational implementations of core Monte Carlo method algorithms
Author-email: Carsten Jørgensen <carstenj@gmail.com>
License: MIT
License-File: LICENSE
Keywords: education,monte-carlo,numerical-methods,sampling,statistics
Classifier: Development Status :: 3 - Alpha
Classifier: Intended Audience :: Education
Classifier: Intended Audience :: Science/Research
Classifier: License :: OSI Approved :: MIT License
Classifier: Programming Language :: Python :: 3
Classifier: Programming Language :: Python :: 3.12
Classifier: Topic :: Education
Classifier: Topic :: Scientific/Engineering :: Mathematics
Requires-Python: >=3.12
Requires-Dist: arviz==0.22.0
Requires-Dist: iprogress==0.4
Requires-Dist: matplotlib==3.10.0
Requires-Dist: numpy==2.0.2
Requires-Dist: pandas==2.2.2
Requires-Dist: scipy==1.16.1
Requires-Dist: seaborn==0.13.2
Requires-Dist: statsmodels==0.14.5
Requires-Dist: tqdm==4.67.1
Requires-Dist: watermark==2.5.0
